README.md
setup.py
scb_payment/__init__.py
scb_payment/authorization.py
scb_payment/business_code.py
scb_payment/constants.py
scb_payment/decorators.py
scb_payment/error.py
scb_payment/qr_type.py
scb_payment/qrcode_payment.py
scb_payment/request.py
scb_payment.egg-info/PKG-INFO
scb_payment.egg-info/SOURCES.txt
scb_payment.egg-info/dependency_links.txt
scb_payment.egg-info/requires.txt
scb_payment.egg-info/top_level.txt